nestbox/__init__.py
nestbox/coordsystem.py
nestbox/cube.py
nestbox/run_optimizer.py
nestbox/sim.py
nestbox/test.py
nestbox/visualizer.py
nestbox-0.1.0.dist-info/LICENSE
nestbox-0.1.0.dist-info/METADATA
nestbox-0.1.0.dist-info/WHEEL
nestbox-0.1.0.dist-info/top_level.txt
nestbox-0.1.0.dist-info/RECORD
