Metadata-Version: 2.1
Name: nestbox
Version: 0.1.0
Summary: Networked consensus coordinate system alignment
Home-page: https://github.com/dgretton/nestbox
Author: Dana Gretton
Author-email: dgretton@mit.edu
License: UNKNOWN
Platform: UNKNOWN
Classifier: Programming Language :: Python :: 3
Classifier: License :: OSI Approved :: MIT License
Classifier: Operating System :: OS Independent
Requires-Python: >=3.6
Requires-Dist: numpy
Requires-Dist: torch
